Metadata-Version: 2.1
Name: dg_probability
Version: 1.0
Summary: Gaussian and Binomial distributions
Author: Shamir Alavi
Author-email: dg1223.dev@gmail.com
